tests
aldryn_installer
