Metadata-Version: 1.1
Name: aldryn-installer
Version: 0.1.1
Summary: Command to easily bootstrap django CMS projects
Home-page: https://github.com/nephila/aldryn-installer
Author: Iacopo Spalletti
Author-email: i.spalletti@nephila.it
License: BSD
Keywords: aldryn-installer
Platform: UNKNOWN
Classifier: Development Status :: 4 - Beta
Classifier: Framework :: Django
Classifier: Intended Audience :: Developers
Classifier: License :: OSI Approved :: BSD License
Classifier: Natural Language :: English
Classifier: Programming Language :: Python :: 2
Classifier: Programming Language :: Python :: 2.6
Classifier: Programming Language :: Python :: 2.7
Classifier: Topic :: Software Development
